picsellia_pipelines_cli/__init__.py
picsellia_pipelines_cli/main.py
picsellia_pipelines_cli/commands/__init__.py
picsellia_pipelines_cli/commands/auth.py
picsellia_pipelines_cli/commands/processing/__init__.py
picsellia_pipelines_cli/commands/processing/deployer.py
picsellia_pipelines_cli/commands/processing/initializer.py
picsellia_pipelines_cli/commands/processing/launcher.py
picsellia_pipelines_cli/commands/processing/smoke_tester.py
picsellia_pipelines_cli/commands/processing/syncer.py
picsellia_pipelines_cli/commands/processing/tester.py
picsellia_pipelines_cli/commands/processing/templates/__init__.py
picsellia_pipelines_cli/commands/processing/templates/data_auto_tagging_template.py
picsellia_pipelines_cli/commands/processing/templates/dataset_version_creation_template.py
picsellia_pipelines_cli/commands/processing/templates/model_conversion_template.py
picsellia_pipelines_cli/commands/processing/templates/pre_annotation_template.py
picsellia_pipelines_cli/commands/processing/utils/__init__.py
picsellia_pipelines_cli/commands/processing/utils/tester.py
picsellia_pipelines_cli/commands/training/__init__.py
picsellia_pipelines_cli/commands/training/deployer.py
picsellia_pipelines_cli/commands/training/initializer.py
picsellia_pipelines_cli/commands/training/launcher.py
picsellia_pipelines_cli/commands/training/smoke_tester.py
picsellia_pipelines_cli/commands/training/tester.py
picsellia_pipelines_cli/commands/training/templates/__init__.py
picsellia_pipelines_cli/commands/training/templates/yolov8_template.py
picsellia_pipelines_cli/commands/training/utils/__init__.py
picsellia_pipelines_cli/commands/training/utils/test.py
picsellia_pipelines_cli/utils/__init__.py
picsellia_pipelines_cli/utils/base_template.py
picsellia_pipelines_cli/utils/deployer.py
picsellia_pipelines_cli/utils/env_utils.py
picsellia_pipelines_cli/utils/initializer.py
picsellia_pipelines_cli/utils/launcher.py
picsellia_pipelines_cli/utils/logging.py
picsellia_pipelines_cli-0.3.2.dist-info/METADATA
picsellia_pipelines_cli-0.3.2.dist-info/WHEEL
picsellia_pipelines_cli-0.3.2.dist-info/entry_points.txt
picsellia_pipelines_cli-0.3.2.dist-info/licenses/LICENSE
picsellia_pipelines_cli-0.3.2.dist-info/RECORD
