Metadata-Version: 2.4
Name: picsellia-pipelines-cli
Version: 0.3.2
Author-email: Sonia Garrouch <sonia.garrouch@picsellia.com>, Pierre-Nicolas Tiffreau <pierre-nicolas@picsellia.com>
Maintainer-email: Sonia Garrouch <sonia.garrouch@picsellia.com>, Pierre-Nicolas Tiffreau <pierre-nicolas@picsellia.com>
License: MIT
License-File: LICENSE
Keywords: cli,computer-vision,cv-engine,picsellia,pipeline,vision
Classifier: Development Status :: 4 - Beta
Classifier: Intended Audience :: Developers
Classifier: License :: OSI Approved :: MIT License
Classifier: Programming Language :: Python
Classifier: Programming Language :: Python :: 3.9
Classifier: Programming Language :: Python :: 3.10
Classifier: Programming Language :: Python :: 3.11
Classifier: Programming Language :: Python :: 3.12
Classifier: Programming Language :: Python :: 3.13
Classifier: Topic :: Software Development
Classifier: Topic :: Software Development :: Libraries
Classifier: Typing :: Typed
Requires-Python: <3.14,>=3.10
Requires-Dist: dotenv<1.0,>=0.9.9
Requires-Dist: picsellia<7.0.0,>=6.20.0
Requires-Dist: semver<4.0.0,>=3.0.0
Requires-Dist: toml<1.0,>=0.10.2
Requires-Dist: typer<0.16.0,>=0.15.2
